CHANGELOG.rst
LICENSE
MANIFEST.in
README.rst
setup.cfg
setup.py
docs/man/xprofile.1.rst
docs/man/xprofilerc.5.rst
test/test_cli.py
test/test_xrandr.py
xprofile/__init__.py
xprofile/__main__.py
xprofile/xrandr.py
xprofile.egg-info/PKG-INFO
xprofile.egg-info/SOURCES.txt
xprofile.egg-info/dependency_links.txt
xprofile.egg-info/entry_points.txt
xprofile.egg-info/requires.txt
xprofile.egg-info/top_level.txt
zsh/completions